[{"request":[{"type":"table","title":"Details","tableData":[{"name":"Method","value":"GET","selector":"request.method"},{"name":"URL","value":"/3n93kd3lf5O45Z65R1b1n41086484daad18e4.jpg","selector":"request.targetUri"},{"name":"Path","value":"/3n93kd3lf5O45Z65R1b1n41086484daad18e4.jpg","selector":"request.path"},{"name":"Body Size (bytes)","value":0,"selector":"request.bodySize"}],"body":""},{"type":"table","title":"Headers","tableData":[{"name":"Accept","value":"*/*","selector":"request.headers[\"Accept\"]"},{"name":"Accept-Charset","value":"ISO-8859-1,utf-8;q=0.7,*;q=0.3","selector":"request.headers[\"Accept-Charset\"]"},{"name":"Accept-Encoding","value":"gzip,deflate,sdch","selector":"request.headers[\"Accept-Encoding\"]"},{"name":"Accept-Language","value":"en-US,en;q=0.8","selector":"request.headers[\"Accept-Language\"]"},{"name":"Connection","value":"keep-alive","selector":"request.headers[\"Connection\"]"},{"name":"Host","value":"images.craigslist.org","selector":"request.headers[\"Host\"]"},{"name":"Referer","value":"http://vancouver.en.craigslist.ca/van/mcy/2175321447.html","selector":"request.headers[\"Referer\"]"},{"name":"User-Agent","value":"Mozilla/5.0 (Windows; U; Windows NT 6.1; en-US) AppleWebKit/534.10 (KHTML, like Gecko) Chrome/8.0.552.237 Safari/534.10","selector":"request.headers[\"User-Agent\"]"}],"body":""},{"type":"table","title":"Query String","tableData":null,"body":""}],"response":[{"type":"table","title":"Details","tableData":[{"name":"Status","value":200,"selector":"response.status"},{"name":"Status Text","value":"OK","selector":"response.statusText"},{"name":"Body Size (bytes)","value":0,"selector":"response.bodySize"}],"body":""},{"type":"table","title":"Headers","tableData":[{"name":"Cache-Control","value":"public, max-age=86400","selector":"response.headers[\"Cache-Control\"]"},{"name":"Content-Type","value":"image/jpeg","selector":"response.headers[\"Content-Type\"]"},{"name":"Date","value":"Tue, 25 Jan 2011 09:04:22 GMT","selector":"response.headers[\"Date\"]"},{"name":"Last-Modified","value":"Tue, 25 Jan 2011 09:04:22 GMT","selector":"response.headers[\"Last-Modified\"]"},{"name":"Server","value":"Apache","selector":"response.headers[\"Server\"]"},{"name":"Transfer-Encoding","value":"chunked","selector":"response.headers[\"Transfer-Encoding\"]"}],"body":""},{"type":"body","title":"Body","tableData":null,"encoding":"base64","mimeType":"image/jpeg","body":"\ufffd\ufffd\ufffd\ufffd\u0000\u0010JFIF\u0000\u0001\u0001\u0001\u0000`\u0000`\u0000\u0000\ufffd\ufffd\u0000C\u0000\u0014\u000e\u000f\u0012\u000f\r\u0014\u0012\u0010\u0012\u0017\u0015\u0014\u0018\u001e2!\u001e\u001c\u001c\u001e=,.$2I@LKG@FEPZsbPUmVEFd\ufffdemw{\ufffd\ufffd\ufffdN`\ufffd\ufffd\ufffd}\ufffds~\ufffd|\ufffd\ufffd\u0000C\u0001\u0015\u0017\u0017\u001e\u001a\u001e;!!;|SFS||||||||||||||||||||||||||||||||||||||||||||||||||\ufffd\ufffd\u0000\u0011\b\u0000\ufffd\u0000\ufffd\u0003\u0001\"\u0000\u0002\u0011\u0001\u0003\u0011\u0001\ufffd\ufffd\u0000\u001b\u0000\u0000\u0002\u0003\u0001\u0001\u0001\u0000\u0000\u0000\u0000\u0000\u0000\u0000\u0000\u0000\u0000\u0003\u0004\u0001\u0002\u0005\u0000\u0006\u0007\ufffd\ufffd\u0000=\u0010\u0000\u0002\u0001\u0003\u0002\u0005\u0002\u0003\u0004\b\u0005\u0004\u0003\u0000\u0000\u0000\u0001\u0002\u0003\u0000\u0004\u0011\u0012!\u0005\u00131AQ\"a2Bq\u0014#\ufffd\ufffdRSbr\ufffd\ufffd\ufffd\ufffd\u0006\ufffd\ufffd\ufffd\ufffd\u0015$4D3\ufffd\ufffd\ufffd\ufffd\u0000\u0018\u0001\u0001\u0001\u0001\u0001\u0001\u0000\u0000\u0000\u0000\u0000\u0000\u0000\u0000\u0000\u0000\u0000\u0000\u0001\u0002\u0003\u0004\ufffd\ufffd\u0000\u001e\u0011\u0001\u0001\u0001\u0001\u0001\u0000\u0003\u0001\u0001\u0001\u0000\u0000\u0000\u0000\u0000\u0000\u0000\u0001\u0011\u0002!\u00121A\u0003Q\"\ufffd\ufffd\u0000\f\u0003\u0001\u0000\u0002\u0011\u0003\u0011\u0000?\u0000\ufffdn\ufffd\u0018\ufffdX\ufffd\ufffdH\ufffd'\u000e\ufffd\u0011\ufffd\ufffdd\ufffd\ufffddq!\ufffd\ufffd}\ufffdw\u003c^o\ufffd̲\ufffd\ufffd\ufffd:\ufffd\ufffd_\ufffd7\ufffdREP\ufffd\u0007T\ufffd\ufffd\ufffdc~uF\ufffd_ֿ\ufffdWU\u0018\ufffd\u0000\u0026\ufffdWJ~\ufffd\u000b\ufffd\ufffd\ufffd;\ufffd\u0011sg\u001a\ufffd\ufffd\u000f\ufffd\u0007:5v\ufffd\ufffd\ufffd[\ufffd\u0026\ufffd\u001e\ufffd7\"\ufffd\ufffd\ufffd\u00177\ufffdKv\ufffd\u0018{g\ufffdo\ufffd\ufffd\ufffd\ufffd9\ufffd\u0012复dYN\ufffd\u0019\u001b\ufffd\u0019\ufffd\ufffd\ufffd\ufffd\ufffd\u0016\ufffdc!Xў\u0017\u001a\ufffdX\ufffd\ufffd\r.\u001aF!\u0011\ufffd\ufffd\ufffd1\ufffd\ufffd\ufffdq$s\ufffd\ufffd6\u0018\ufffdR\u003c\ufffd\ufffd~\ufffd)\ufffd\ufffd\u001a\ufffd\ufffd\ufffd\ufffd\u003e\ufffd\ufffd\u000e\ufffd\u0007\ufffdg\ufffdz\u001fz\ufffd\ufffd\ufffdR\ufffd2f|g\ufffdV\ufffd7\u000eű+\u001f\ufffdV\u000f0\ufffd\u0019=렺\ufffd\ufffd*\ufffdc\ufffdVn\ufffd\u001e=\u0019\ufffd\ufffde\ufffdoϭJI;\u0010\ufffd#(\ufffd\ufffd\ufffd\u0000Z\ufffd\ufffdl\ufffd\ufffdi\u0012E=3\ufffd\ufffd6\ufffdI\ufffd\ufffdb]\ufffdԑқ\ufffd\u001a\ufffdp襚Fң'z]8\ufffd9\ufffd@\ufffd\ufffd\ufffd\ufffdU\ufffd\ufffdA\u0019\ufffd\ufffdc\ufffd\ufffd\ufffd\ufffd\ufffd\u0002c\ufffd\ufffd\ufffdq\ufffd\ufffd\ufffd[\ufffd۞\ufffd\ufffd^\ufffd*V\ufffdA\ufffd\ufffd}Meq;֍\u0011!b\ufffd\ufffd\":\ufffd|w\ufffd\ufffd\u0017\ufffdY\ufffd\ufffd\u0007\ufffdk\ufffdD,\ufffd0\u0002\ufffd;ƕu$\ufffd\ufffdz\ufffdk\ufffdA~%mZ\ufffd\ufffd\ufffdb\ufffd\ufffd\ufffd\u0015C\u0010\u0000\ufffd\ufffd\u0007/\ufffd.\u003e\ufffdR\u0016}Nt\ufffd|\ufffd\ufffd\ufffd!\ufffd\ufffdb\ufffdIu|\ufffd\u0018\ufffd\ufffdִ|B\ufffdF\n\ufffdz\ufffd\ufffd0\n\ufffdL\u001a\u0005l\ufffd\ufffd=rM#9\ufffd\ufffd\ufffdV\ufffd\ufffdF\ufffdHĭ\ufffdq\ufffdU\u003c\u0005f\ufffdB\ufffd\ufffd\n\ufffd\ufffd\ufffd4\ufffd\u0026\ufffd\ufffdQ%\ufffd\ufffd\ufffd\ufffd\u001c\ufffdi\ufffd\u003e#]U\ufffdY\u0018\ufffdB\ufffd\u0007\ufffd\ufffd\ufffd\ufffd\ufffd\ufffd|F\ufffd\ufffd\ufffd\ufffd\u0015\ufffd5jI\ufffd\u001a\ufffd\ufffd^\ufffdw\u0015\ufffd\ufffdc\ufffd\ufffd\ufffd\"\ufffd\ufffd\u003cpƾ\ufffdlV\ufffd\ufffd\ufffdcoQw\u001fZ\ufffd\ufffd\ufffdk;\ufffd4aX\ufffdF\rn\ufffd\ufffd*8\ufffdx\u0026UIG\ufffdt\ufffd\u0015ϙ\u001d:\ufffd\u001fa\ufffd\\\ufffd0~\ufffd\u003c\ufffdQ\ufffdU\u001f\ufffd6\ufffdU\ufffd\ufffd\b\ufffd\ufffd\ufffdiI\ufffd\ufffd]9Uԇ*H\ufffdjl\ufffdgg\ufffdL\ufffd\u0014\ufffd\ufffd\ufffd\ufffd\ufffd\u0011Ȗ1\ufffd\ufffd\ufffd\ufffd\u0000\ufffd\ufffd\ufffd\ufffd\ufffd\ufffd\ufffdG\ufffdǃ\ufffd\ufffd\ufffd\u0000Z˅\ufffdw\ufffd\u000e={\ufffd\ufffdK\ufffdoW\ufffd7fR\u000e\u003ct5\ufffduo$\u0007^\ufffd\\{1\ufffd\ufffdޥQ\ufffdmĳ3G'\ufffd(Σֳ\ufffd\ufffd\ufffd\ufffdˌ\f\ufffd~\ufffd\ufffdW\ufffdA\u0026QO\ufffdz\ufffd\ufffd\u000b\ufffd\ufffd\ufffd\u0007,\ufffdb\ufffd@\ufffd4\u001936@\u00148ݣmHpk\ufffdp\ufffd\ufffd\b\ufffd\ufffdܛc6\ufffd\ufffd2\ufffd\ufffd^v\ufffd-九\ufffdm\u0010\ufffdm\u0000\r\ufffd\ufffd\ufffd\u0010).\ufffdH\ufffd\u003e\ufffd«o3C(t\ufffd\ufffd\f'\ufffd`j\u0004o\ufffd\u0018\u0003\ufffdP\ufffd\ufffds.\ufffd\ufffd\u001ei\ufffd\u001e.\ufffd\ufffdrQ4\ufffdŘ\ufffdj\ufffdӍJA8Ӝ\u001af\ufffd\ufffdk@\ufffdl\ufffdo\ufffdm\ufffdoj\ufffdD\ufffd\ufffdE\ufffdx$d\ufffd\ufffdǐv\ufffdbH\ufffd\ufffd\u000b\ufffd\ufffd\ufffd\u0002I\ufffd\ufffdy%\ufffdwf\ufffd\u0012;Ӌ\"_)I\u001b\ufffd\ufffdl\ufffd\ufffd\ufffdԺ\ufffdh\ufffd\ufffd\ufffd6\ufffd\ufffd\ufffdY׎$\ufffdvBpwޘn\u001b\ufffd\ufffdn#\ufffdt\fE'2\bئ\ufffdJ\ufffd\ufffdw\ufffdȩ!\u0011\u0005\ufffdp\ufffd\ufffd\ufffdh\ufffd\ufffd0_Pm=\u0000\ufffd\ufffd\ufffd$\u0003\ufffd\u001bS1,\ufffd\ufffdTa\ufffd\ufffd\ufffd\ufffdll\ufffd\ufffd\ufffd*\ufffdQ%\ufffd+\ufffdy\ufffdnl\ufffdɣ^O\ufffdkLLD`6\ufffdv\u001fZ_\ufffdV}\ufffd{\ufffd\ufffd:A\ufffdT\ufffdN\\\ufffdρ\ufffd\ufffd\ufffd\ufffd\\G\u0012-\ufffdE\ufffd=DWW\ufffdk\ufffd\ufffd\ufffdÒ?\ufffdԭ\ufffd2\u0003\"\ufffd'\ufffdiI$\ufffd\u001a=\ufffd\ufffdFev\ufffd\r\ufffd{\ufffd\u0011\ufffd\ufffd\ufffdx\ufffdo\u0004d\u0003\ufffd1D\ufffd\ufffd\ufffd\u0016\ufffdA\u0002F\ufffdӕ\u0018ڻ\ufffd\ufffd\ufffd\ufffd֢h\ufffd\ufffd\ufffd\ufffd\ufffd\u0026\ufffdZCj^\ufffd\u001f\ufffdF\ufffd\ufffd(D\ufffd\ufffdmFaC#j\ufffd\ufffd\ufffd\u0016\ufffd\u0007\ufffdL\u0000\ufffd\ufffd\ufffd\ufffd_\ufffd\ufffd\u001dġ\ufffd\u001c\ufffd\ufffdִ\u001cd\u0010Fǭf]\ufffd\ufffd3\u0017U\ufffd\ufffd'\ufffd\ufffdP!od\ufffd\ufffdec\ufffd\ufffd{\ufffdR\ufffdH\ufffdE4J\ufffd\ufffd\ufffden→\ufffdubq\ufffdI\ufffd3\ufffdLǮ\ufffd{\n\ufffd\ufffdf\ufffd\ufffd\u001c\ufffdt\u001f\ufffdJB\ufffd\ufffdm\ufffd\ufffdH\ufffd%\ufffd\u001auK\u0026\ufffd`)iaT;\u0012i\ufffd\ufffd`x\ufffd\u00191\ufffd\u003e\"NƯn\ufffdF\ufffd\u0019\ufffdf\u003e\ufffd\ufffd\ufffd\ufffd\ufffd\ufffd\ufffd\ufffdm\ufffd~4\u0007r\u0016BA\ufffd\ufffd\ufffd|\u0026\ufffd\ufffd\u0014\ufffd\ufffd+\ufffd\ufffd#j+\ufffd\ufffd\u001ej\"~Yΐ|oҠdȭ70|\ufffd\u000b}{\ufffd\ufffd\ufffd!\ufffd\ufffdW\u0017\ufffd\ufffd\ufffd\u000ej\u0011\ufffd\u003e\ufffd\ufffdހ\ufffdQ\ufffd\u001aF*\ufffdg\ufffd2~\ufffd\u000bo\ufffd\ufffd\ufffd\ufffd\u001b\ufffd\u001aV#O@h\ufffdڈ`\ufffdl\ufffd\u001f\u0014\u0005\nT|n\u003e\ufffd\b\ufffd\ufffd̤+\ufffd\ufffdF\u001d\rB\ufffd\ufffd$\ufffd\u001a\u001fX\ufffd?\ufffd\u003e\ufffdE\ufffd}s\ufffd\ufffd\u0026\ufffd8T\ufffd\ufffd剿\ufffd\ufffds\ufffd\ufffd\ufffd-\ufffd\ufffd5\ufffd\ufffd\ufffdX\ufffdc\ufffd\ufffdO\ufffdk=\ufffd\u001d\ufffd6\ufffd?\u001e\ufffd\u0016hI\u0010\ufffd\ufffdw\ufffdv\ufffd\ufffd5*\ufffdG\u0015\ufffd\ufffd\u0013c\ni\u0015ep\ufffd\u0007\ufffd\ufffd\u0000\ufffdr\ufffdH\ufffd\ufffd:S\ufffd\ufffd\u0012\ufffd\ufffd\u001bQ;\ufffd\ufffdX7\ufffd\ufffdh͙ctՁ\ufffd\ufffd_\ufffd\ufffd[\ufffd=e\ufffd\ufffd]\ufffd$C\ufffdG\ufffd\ufffd:\ufffdW\ufffd\ufffd\ufffdU\ufffd.\ufffd6L/\ufffd\ufffd\ufffd\ufffd\ufffd_\\i\ufffd\ufffd\ufffd\t\ufffd\ufffdʕ\ufffd橞\ufffd\ufffd\ufffd\ufffdA݄\ufffd\ufffdF\ufffdQ@\ufffd-s{\u0003\ufffd\ufffdH\ufffd\ufffd\n᎖\ufffd\ufffd\ufffdw\u0003a\ufffd\u00039\ufffd\ufffdۖԩӨ_\ufffdbuǧ\ufffd\ufffd\ufffd\u003c\ufffd\ufffdA~'r\ufffdg_md\ufffd?\ufffd\u0017\u0007\ufffd\u0000f_\ufffd4\u0007\ufffdD8*hd\ufffdb\ufffdᆗ\ufffd\\\ufffd\ufffds\u0026x֭\ufffd\ufffd\ufffd+y-o0\u001bNC\ufffd\ufffd\ufffd\ufffd\ufffd\ufffd\ufffd\ufffd\r\ufffdcPZx\ufffd\ufffd\ufffd\ufffdi2U\ufffd\ufffd[c[\\?\ufffd\ufffd\ufffdt\ufffd\ufffd-X\ufffdR\u0006q\ufffd\ufffd\ufffd35eĭk\ufffd\ufffd\ufffd\ufffd\u001cе;n\ufffd\ufffdު\ufffd\ufffdc\ufffdE\nV\ufffdQ-\ufffd\u0013\u003e\ufffdm\nz\u0013\ufffd\ufffdmj\ufffd}\ufffd\ufffd1\ufffd\ufffd\ufffd\ufffds \u0007J\ufffdE\u0001\ufffd\ufffd\ufffd\u001ez\ufffdF\u000b\u0001]\ufffd\ufffdGT\ufffdu\ufffd\ufffd(8\u0010\u001bu\ufffd\ufffdF\ufffd')\ufffdpݨJ\ufffd\ufffdEE\ufffd5o\ufffd\ufffd\u000b6\ufffd\u001b~\u0014M\ufffdo\ufffd\ufffd\ufffdU\u0014\ufffd\ufffd\ufffd\ufffd\ufffd\ufffd\ufffd\ufffd\ufffd9f\ufffd\ufffd\ufffd@K5y'E\ufffd\ufffd\ufffd\ufffd\ufffdQáq\ufffd\ufffd\u001c\ufffd\ufffd\ufffd\ufffd\ufffd*gc\ufffd4\ufffd\ufffd\fע\ufffd\ufffdh\ufffd5:9y\ufffd\u001dk\ufffd\ufffd*\ufffd\ufffd\ufffdse\ufffd5\u0004\"t\ufffd*\ufffdz\u0003\ufffd\ufffdi@\ufffd\u0000ں\ufffd\ufffd\ufffd\ufffdo\ufffd\ufffdH\ufffdu.]\ufffd\ufffdz\ufffd\u0010R{S\u0013\ufffd\u0017\u0012\ufffd\ufffd\ufffd\u0000V\ufffd\ufffd\u0003\ufffd\u0015\ufffd\ufffdx\ufffd\ufffdh\ufffd!gUS\ufffdQ\ufffdI\ufffd@\ufffdv\ufffdFo\ufffd\ufffd\u0014\ufffd\ufffd\u0010\u0026\ufffd\ufffd\u001dico\u0026\u0018\ufffd,\u0000\ufffd4\u0013z \\\n\ufffd\u003cI0N\ufffd\u0003\ufffdn\ufffd\u0007gά\ufffd\ufffd֛\ufffd\ufffd̠\ufffdiy\ufffd\ufffdM\ufffd\r\u001fq@\ufffd\ufffdNH\u001f\ufffd48u\ufffdDdX\u0018\ufffd3׵9ol\ufffd\ufffd\ufffd\ufffd\ufffdTX\\\ufffd\ufffd\nv\u001f\ufffd\ufffdҭ\ufffd\ufffd\ufffd.\u001d\ufffd\u001b\fx\ufffd3\ufffdx\ufffdE\u0026\ufffd\ufffddWr\ufffd\u001d\u003e\u0013\ufffdRU#b\ufffd\u0019\ufffd\ufffd\ufffd\ufffd\ufffd\ufffdPͨ1\ufffd\ufffd^\u000btծm\ufffd\ufffdj\ufffd\ufffdʨV9\u0003'5\u0013\ufffdTl(\ufffd\\\\ka\u0012\u00105\u001cR\u000e\u0015_}\ufffd\ufffd\ufffd:\ufffdN|\ufffd\u0018\ufffdl\ufffd\u001c\ufffd.\ufffd\ufffd\ufffdӵ@\ufffd\ufffd\ufffd\u0019q\ufffd\u001e\ufffd\ufffd\ufffd\ufffd\ufffdр\u00148\ufffd,\ufffd`\ufffdW\u0005\ufffd\u0005\ufffd\u000b\ufffd\ufffd\u0014\u0011\ufffd\u003c\u0016\ufffd\ufffd\ufffdW\u0011\ufffd'\ufffd3c\ufffd\ufffd\ufffd\u001a_Jv^\ufffdL\ufffd\ufffd\ufffdU\ufffd\ufffd_B\ufffd_O\ufffd\ufffd\ufffd\ufffdϝ\ufffd\ufffd\ufffd-\ufffdv\ufffd\ufffdի\\\ufffd\ufffd\f\u0011\ufffdbD\u001f(\ufffd3\ufffd+\u001cû\ufffd\ufffd\ufffd\ufffd޺\ufffd5\ufffd\u0016\ufffd\u00138R\ufffd+\ufffd~9\ufffd$\ufffd\u0000\ufffd\u0012\ufffd\ufffd\ufffd`\ufffd.?\ufffd%\ufffd\ufffdC\ufffd\"j«PuP\u0017 UZP\ufffd\ufffdCU\u0018\u001e檥\ufffd,v\ufffd\ufffd|\ufffdVHn5\ufffd\u001a\ufffd\ufffdԏKy\ufffd\ufffdԎ\ufffd\u0003޴\ufffd\u0019\ufffd\ufffdT\ufffd)*\ufffd\ufffd\u000b\u0000\ufffd{\ufffd@\ufffdݜV\ufffd\ufffdwi\ufffd\u0004\ufffd\ufffd-\ufffd\ufffdc\ufffd\ufffdt\\+`\ufffd:\ufffd޷\ufffd\\J\u000b\ufffd\u0014\u0016\ufffdZ8s\ufffd\ufffdO\ufffd`6\ufffd\ufffd\ufffdE\u0012\ufffd\u0019\u0012F.5\ufffdP\ufffd\ufffd\ufffdR\ufffd\ufffdF:\ufffdt\u0016܍\u001d\r\u0005\u003e5\ufffdw\ufffd\ufffdi\ufffdOLnM\u0014I-V\u0016M%\ufffd\u000e\ufffdYH\u0003VA\u0000\ufffdP\ufffd\ufffd\ufffd9\u0018\u0007bh\ufffd\ufffdͲI\u0011S\ufffdă?Π\u0002\\\ufffd\ufffd|\ufffd\ufffd\ufffd\ufffd\ufffd\ufffd,\ufffd+\ufffd\r\ufffdA\ufffd\ufffd\ufffd?\u0011\u0003\ufffdj\ufffd\u0019z\"\ufffd0\u0002\ufffd\ufffd@ۯ\ufffd捔\ufffd*R2N\ufffdj(\ufffd.\u0017'\ufffd\u0018\n\ufffd\u0014X\ufffdi\u001c$jY\ufffd@*\u000e\u000b\ufffd\ufffdRˆi\u001cۅ\u0007\ufffdP\ufffd\u0007֜\ufffd\ufffd1mG6\\\u003c\ufffd\ufffdi~%t\ufffd\ufffdY\t20\ufffd\ufffdh\ufffd\ufffdK\ufffd\u0002\ufffda\ufffd9\ufffd\ufffd\ufffd\ufffd\ufffd\ufffd\ufffd\ufffdf{\ufffd|b8W\ufffdcX.K\ufffd\ufffd\u0012O\ufffdƽ\ufffd\ufffdv\ufffd\ufffd\ufffd.2F\u001a_Y\ufffd\ufffd\ufffd\ufffd\ufffdV\ufffd\ufffd\ufffd\ufffdD\ufffd(\u0026eD\ufffd\ufffdl\ufffd%\ufffd\bΆ95\ufffdDӻ}\u003c\ufffdFmd_Z\ufffd\ufffd_\ufffd\ufffd\ufffdP`\u0026\ufffdں\ufffd\ufffdn\ufffd\ufffd\ufffd\u001aǞ\ufffd\ufffd]S\u0015\ufffd'_\ufffd\ufffd?x\ufffd4\ufffdS\u0013\ufffd\ufffd\ufffd\ufffd\ufffd\u000f\ufffdi\ufffd4\ufffdU\ufffd\u001c\ufffdhf\ufffd\ufffdWF\ufffdߦ\ufffdz \ufffd\ufffd\ufffd\ufffdV*\ufffd\tGS\ufffd\ufffd|ͽí\u001by\ufffdY\ufffd\ufffd\u0019?\ufffdZ@ą\ufffd\ufffd\ufffd\u0007\ufffd8-\ufffd\ufffd+F\ufffd\ufffd\ufffdZ\u0000M1\u0016\u000b\ufffdl)Ł\ufffd\ufffd2\u0017Hӗo'\ufffd*)H\ufffd\ufffdl)8\ufffd١͝Ym\ufffd@+G\ufffd\ufffd$k\t\ufffdX\ufffd\ufffd\ufffd\ufffdg\ufffdHďI\u0019\ufffd\ufffd3\u0002\ufffdpj\ufffd\u001b0\ufffdjib_\ufffdU\ufffd(\u0000\ufffd\ufffd\ufffdz\u0026\ufffdx\ufffd\ufffd0n\ufffdZ\ufffdUt\ufffd\ufffd\ufffd\u000e\u0019\ufffd忓`R\u0010}R\ufffd\ufffd\u0000\ufffd\ufffd\u0026\ufffd\ufffdE\u0002廞\ufffd=\ufffd\ufffd\ufffdp\ufffd\ufffdt{\rR\u0011\ufffdr?\ufffd\ufffdW\t\ufffd\ufffd\ufffd\ufffd\u0017-z\ufffd\ufffdX\ufffd\ufffd\ufffd\ufffd\u000eK;\u001c/\ufffdE\ufffdS\ufffd\ufffd\u000be\ufffd\ufffd+\ufffdי\ufffdV\ufffdB\ufffdr\ufffdD\ufffd\ufffdi\ufffd.\ufffd\ufffdx\u0014$^\ufffd\ufffdjF-\u001b\ufffd\ufffd\u001b\ufffd\ufffd`\u001f;z\ufffd\ufffdz\ufffdWQ\ufffd\ufffdr\ufffdjBI\ufffd\b|VG\u0001\ufffd\ufffdk\u0017ڦ\ufffd\ufffd\ufffd\ufffd.\ufffd\n\ufffd\u0000\ufffdk\ufffdO\ufffd\ufffd_\ufffd\ufffdVt\ufffd'\u0015\ufffdq\ufffd\ufffdj\ufffdw\ufffd\u0001\ufffd\ufffd\ufffdD\ufffdf)\f\ufffd1\ufffdɾ\u003c\u001e\ufffdY\ufffdlO\u0002\ufffd\tS\ufffdV\ufffdֆ\ufffd1C\u001e\u0019䕆ꥱ\ufffd3\ufffd7\ufffd7\u001c\ufffd\u000b\b\ufffdX8=N+\ufffd[K\ufffdQX\u003eP\ufffd~\ufffd5՟\ufffd?\ufffd\ufffd\u0026_\ufffd\ufffd\ufffd\ufffdT\ufffd\ufffd#\u0006\ufffd\ufffd\u003e\ufffd\ufffd\ufffd\ufffdG/5\ufffd\ufffd\ufffd\ufffd\ufffd4\ufffd/j\ufffd\u001cm@\u001cc\ufffdVEԭ\ufffdV\ufffd\ufffd\ufffd\u0012%\ufffd\ufffd\u001e\ufffdU\t\\\ufffdc;\u000f\ufffdg\ufffdH̥c%s\ufffdGz՚0X\ufffdJ7\u00103\ufffd\ufffd)j\ufffd\ufffd4r\ufffd\ufffdy\ufffd\u0013\ufffdB\u0013}\ufffd\ufffd=\ufffd\ufffd\ufffd\ufffd\ufffd\ufffdN(g-QQ\ufffd͓G\u0003\b(q\ufffd0#\u0026\ufffdX\ufffdU\ufffd\\\ufffdac\ufffd\ufffd\ufffdP/\ufffd\ufffdS\ufffd\ufffd\u0011\ufffdV\ufffd\u000b\ufffd\ufffdi\ufffd\ufffd}\ufffd?\ufffd\ufffd\ufffd8W\u0005k\ufffd3N\nA\ufffd޽ X\ufffd\ufffd\"*\ufffd\ufffd\ufffd\r\ufffd^@\ufffd\ufffd\ufffd\u0001U\ufffd5\u0017\u0002\ufffd\ufffd\ufffd7`\u0000\ufffd\ufffd\u0015\ufffd\ufffd.\r\ufffd`dF\ufffd\ufffd?\ufffd\u001a\ufffd\ufffd\ufffd\ufffd\u0014\ufffd\u0001\ufffd\ufffd\ufffdƯ\ufffdY\u0012\ufffd@'\ufffdߵ{A¬\ufffd\ufffd\ufffdy\u0000\ufffd\u0012\u000fR\ufffd\ufffd_5\ufffd\ufffd\ufffdi\ufffdH\ufffd9c\ufffd\ufffd\ufffd\ufffd\ufffd\"04\ufffdP0\ufffd\ufffd\u0015Y\u00128\ufffd #\ufffd\ufffd\f\u0000\ufffd\ufffd\ufffd\u001f\b\ufffd\u0018\ufffd\u001fʬ\ufffd\ufffd¶\ufffd\ufffd\ufffd,9,%b\ufffd\ufffd\u0000:ʕ\ufffd\ufffd1C\ufffdS\ufffd\ufffd\u0001\ufffd\ufffd\ufffd#\ufffdi\u000e\\kf\ufffd\u00198t\f=+\ufffd\ufffd\ufffd#/\r\ufffd\u0026\ufffd\u001e\ufffd\ufffdҳ׫\u0012\ufffd,\ufffdTc\u0003\ufffd\ruZ'\n4\ufffdF?:\ufffd\ufffd\ufffd_\u0018FH\ufffd\ufffdϽF\ufffdt\ufffd^\ufffd\ufffd\u0016s\ufffd_ʮ\u0011\u0017\ufffd\ufffd\ufffd\u0015\ufffda\ufffdyNz#~Uaa1\ufffdD\ufffd\u0000\ufffd^\ufffd\ufffd\ufffd\u0006OJ\u000f-5\ufffdЁ\ufffd\u0026Q\ufffd\ufffdr\ufffdNX\ufffd\ufffdZ\ufffd\ufffd}\ufffdR~Q\ufffd\ufffdM\ufffdS\ufffd\ufffd@\ufffd\ufffdՆ\u001b\ufffdjΟչ\ufffd;\ufffdوx\ufffd\u0006KTl\ufffdEha\u0014\ufffdX\ufffd\u001d\ufffdkX\ufffd\ufffd\ufffd5u\ufffdU\ufffdS\u0014\ufffdV\ufffdnh\ufffd\u0019Ӻ\ufffd\ufffd\ufffd\ufffd\b\ufffdژ\ufffd[\ufffdWH\u001aF\b\ufffdY\ufffd@)\ufffd\ufffd\ufffd\ufffd#R\ufffdlX\ufffd\ufffd\u0002\ufffd\ufffd!\ufffdƪ\u0005\ufffd\ufffdb[bI\ufffd\ufffd\ufffd\ufffd\ufffd뾐k\ufffd\ufffd\ufffdsI\ufffd5\ufffd\ufffd\ufffdO\ufffd\ufffdX\u003cJ\ufffd\ufffd\u0018\ufffd\ufffd~*5\ufffd\ufffd\u001c\u0026\ufffd3\ufffdg\ufffd+y\u0002\ufffdʨ\u0000\ufffdթ\ufffdZC\u0019\ufffdt\ufffd\u0001Fks\u001cJ\ufffdR\u001b\ufffd;\ufffd\ufffdi\ufffd\ufffd\u0001\ufffdܧ\ufffdC\ufffd\ufffd\ufffd\ufffd\ufffd|5#\ufffd\ufffd\ufffd\ufffd3\ufffdq\ufffd˞\ufffd\ufffd\ufffd\ufffd\ufffdF\ufffdΣ\ufffd\ufffdJ(P\u0000\u0000\u00000\u0000\ufffdV\u0015\ufffdU\ufffd\r\ufffd\ufffdTT\u0015\r\ufffd\ufffdZ\ufffd\ufffd7Z\ufffda\ufffdV\ufffd@-\n\ufffd\ufffdE?Q]E\ufffd\ufffd\ufffdk\ufffd\ufffd\ufffd\ufffd\ufffd/\ufffd\ufffd\ufffd)\ufffd\ufffdni9q\ufffd:\ufffd\ufffd\ufffdVl\ufffd\ufffd\ufffd\u0005\ufffd\ufffdt\ufffdym\ufffd\ufffd\ufffd\ufffd\ufffd\ufffd~\u0013T\b\ufffd\ufffdV/\ufffd\ufffd|\ufffdB#\ufffd\ufffdR\ufffdY\u0006B\ufffd{\ufffdg2\ufffd]\ufffd\ufffd\ufffd\f\ufffd\ufffd\ufffd\u0005\u0002[9\"\u003e\ufffd$y\u0014\t\u0014\ufffd\u001e\ufffd\ufffd\ufffdl.\u0015{\ufffdS\ufffdo\u001bV\ufffd\ufffd\u0006\ufffd*ã\u001a\ufffd\u0017ٖ\u0014\u000b\ufffd.w\u0019\ufffd\\\ufffdn\ufffd\ufffdo\u0002\ufffd\ufffd\"Ti\ufffdIIn\ufffd\ufffdb\u0006\ufffd\ufffd#\ufffde\ufffd\ufffd\ufffdOI\ufffdd_\ufffd\b\ufffd\ufffd\ufffd\u001e\ufffd\ufffd\ufffd3}\ufffd2[\ufffd\ufffd\ufffd\ufffd\ufffd\ufffd\u0026\ufffd\ufffd\u0000\u0015\ufffd\u0012ա\ufffd\ufffdn\u0002.\ufffd9\ufffd{V\ufffd͔\ufffd\u0019\ufffd2\ufffd\ufffdE\ufffd\ufffd\ufffd+\ufffd\r\ufffd\ufffd\u003c\ufffd\ufffdD[\ufffdYwo\ufffdjߙV\ufffdb\u0010\ufffd\u0000Z\ufffd\ufffd\u0006[s\ufffd(\ufffdu3c\u001e\ufffdש\ufffd\ufffdKej\ufffd\r۫\ufffd\u0026\ufffdඅ\ufffd\ufffd\ufffd^\ufffdF\u000f\ufffd\ufffd\ufffd\ufffd]S]]Puuuu\u0004b\ufffdlj\ufffd\u0006\ufffdk\ufffd\u0007M\ufffd\ufffd?\ufffd\ufffd","selector":"response.content.text"}],"event":null,"data":null}]