[{"Protocol":{"name":"redis","version":"3.x","abbr":"REDIS","longName":"Redis Serialization Protocol","macro":"redis","backgroundColor":"#a41e11","foregroundColor":"#ffffff","fontSize":11,"referenceLink":"https://redis.io/topics/protocol","ports":["6379"],"priority":3},"Capture":"pcap","Timestamp":-6795364578871,"ConnectionInfo":{"ClientIP":"1","ClientPort":"1","ServerIP":"2","ServerPort":"2","IsOutgoing":false},"Pair":{"request":{"isRequest":true,"captureTime":"0001-01-01T00:00:00Z","captureSize":0,"payload":{"method":"SET","url":"","details":{"type":"Array","command":"SET","key":"key","value":"value","keyword":""}}},"response":{"isRequest":false,"captureTime":"0001-01-01T00:00:00Z","captureSize":0,"payload":{"method":"","url":"","details":{"type":"Simple String","command":"","key":"","value":"","keyword":"OK"}}}},"Namespace":""},{"Protocol":{"name":"redis","version":"3.x","abbr":"REDIS","longName":"Redis Serialization Protocol","macro":"redis","backgroundColor":"#a41e11","foregroundColor":"#ffffff","fontSize":11,"referenceLink":"https://redis.io/topics/protocol","ports":["6379"],"priority":3},"Capture":"pcap","Timestamp":-6795364578871,"ConnectionInfo":{"ClientIP":"1","ClientPort":"1","ServerIP":"2","ServerPort":"2","IsOutgoing":false},"Pair":{"request":{"isRequest":true,"captureTime":"0001-01-01T00:00:00Z","captureSize":0,"payload":{"method":"GET","url":"","details":{"type":"Array","command":"GET","key":"key","value":"","keyword":""}}},"response":{"isRequest":false,"captureTime":"0001-01-01T00:00:00Z","captureSize":0,"payload":{"method":"","url":"","details":{"type":"Bulk String","command":"","key":"","value":"value","keyword":""}}}},"Namespace":""},{"Protocol":{"name":"redis","version":"3.x","abbr":"REDIS","longName":"Redis Serialization Protocol","macro":"redis","backgroundColor":"#a41e11","foregroundColor":"#ffffff","fontSize":11,"referenceLink":"https://redis.io/topics/protocol","ports":["6379"],"priority":3},"Capture":"pcap","Timestamp":-6795364578871,"ConnectionInfo":{"ClientIP":"1","ClientPort":"1","ServerIP":"2","ServerPort":"2","IsOutgoing":false},"Pair":{"request":{"isRequest":true,"captureTime":"0001-01-01T00:00:00Z","captureSize":0,"payload":{"method":"GET","url":"","details":{"type":"Array","command":"GET","key":"missing_key","value":"","keyword":""}}},"response":{"isRequest":false,"captureTime":"0001-01-01T00:00:00Z","captureSize":0,"payload":{"method":"","url":"","details":{"type":"Bulk String","command":"","key":"","value":"","keyword":""}}}},"Namespace":""}]